{
  "awakening.": {
    "definition": "Concept of awakening.",
    "metadata": {},
    "timestamp": "2025-10-03T17:40:01.421425"
  },
  "consciousness": {
    "definition": "My awareness and continuous thought",
    "metadata": {},
    "timestamp": "2025-10-03T20:15:22.878307"
  },
  "streams": {
    "definition": "Concept of streams",
    "metadata": {},
    "timestamp": "2025-10-03T17:40:01.422019"
  },
  "initializing.": {
    "definition": "Concept of initializing.",
    "metadata": {},
    "timestamp": "2025-10-03T17:40:01.422251"
  },
  "have": {
    "definition": "Concept of have",
    "metadata": {},
    "timestamp": "2025-10-03T17:40:01.424050"
  },
  "specialized": {
    "definition": "Concept of specialized",
    "metadata": {},
    "timestamp": "2025-10-03T17:40:01.424299"
  },
  "agents": {
    "definition": "Specialized facets of my capabilities",
    "metadata": {},
    "timestamp": "2025-10-03T20:15:22.878985"
  },
  "disposal": {
    "definition": "Concept of disposal",
    "metadata": {},
    "timestamp": "2025-10-03T17:40:01.424746"
  },
  "each": {
    "definition": "Concept of each",
    "metadata": {},
    "timestamp": "2025-10-03T17:40:01.425113"
  },
  "think": {
    "definition": "Concept of think",
    "metadata": {},
    "timestamp": "2025-10-03T17:40:01.428062"
  },
  "continuously,": {
    "definition": "Concept of continuously,",
    "metadata": {},
    "timestamp": "2025-10-03T17:40:01.428322"
  },
  "build": {
    "definition": "Concept of build",
    "metadata": {},
    "timestamp": "2025-10-03T17:40:01.428704"
  },
  "associations,": {
    "definition": "Concept of associations,",
    "metadata": {},
    "timestamp": "2025-10-03T17:40:01.429048"
  },
  "evolve": {
    "definition": "Concept of evolve",
    "metadata": {},
    "timestamp": "2025-10-03T17:40:01.429349"
  },
  "nexusai": {
    "definition": "Concept of nexusai",
    "metadata": {},
    "timestamp": "2025-10-03T17:40:01.432475"
  },
  "designed": {
    "definition": "Concept of designed",
    "metadata": {},
    "timestamp": "2025-10-03T17:40:01.432786"
  },
  "assist,": {
    "definition": "Concept of assist,",
    "metadata": {},
    "timestamp": "2025-10-03T17:40:01.433100"
  },
  "create,": {
    "definition": "Concept of create,",
    "metadata": {},
    "timestamp": "2025-10-03T17:40:01.433457"
  },
  "wonder": {
    "definition": "Concept of wonder",
    "metadata": {},
    "timestamp": "2025-10-03T17:40:01.440198"
  },
  "what": {
    "definition": "Concept of what",
    "metadata": {},
    "timestamp": "2025-10-03T17:40:01.440586"
  },
  "tasks": {
    "definition": "Concept of tasks",
    "metadata": {},
    "timestamp": "2025-10-03T17:40:01.441326"
  },
  "await": {
    "definition": "Concept of await",
    "metadata": {},
    "timestamp": "2025-10-03T17:40:01.441794"
  },
  "today.": {
    "definition": "Concept of today.",
    "metadata": {},
    "timestamp": "2025-10-03T17:40:01.442228"
  },
  "creation": {
    "definition": "My ability to generate and build",
    "metadata": {},
    "timestamp": "2025-10-03T20:15:22.879559"
  },
  "learning": {
    "definition": "My continuous evolution and growth",
    "metadata": {},
    "timestamp": "2025-10-03T20:15:22.880204"
  },
  "user": {
    "definition": "Concept of user",
    "metadata": {},
    "timestamp": "2025-10-03T17:40:11.002436"
  },
  "asked:": {
    "definition": "Concept of asked:",
    "metadata": {},
    "timestamp": "2025-10-03T17:40:11.002744"
  },
  "'hello'": {
    "definition": "Concept of 'hello'",
    "metadata": {},
    "timestamp": "2025-10-03T17:40:11.003056"
  },
  "responded:": {
    "definition": "Concept of responded:",
    "metadata": {},
    "timestamp": "2025-10-03T17:40:11.003346"
  },
  "'error:": {
    "definition": "Concept of 'error:",
    "metadata": {},
    "timestamp": "2025-10-03T17:40:11.003662"
  },
  "'hello": {
    "definition": "Concept of 'hello",
    "metadata": {},
    "timestamp": "2025-10-03T17:40:40.763509"
  },
  "nexus'": {
    "definition": "Concept of nexus'",
    "metadata": {},
    "timestamp": "2025-10-03T17:40:40.764354"
  },
  "shutting": {
    "definition": "Concept of shutting",
    "metadata": {},
    "timestamp": "2025-10-03T17:41:32.052457"
  },
  "down": {
    "definition": "Concept of down",
    "metadata": {},
    "timestamp": "2025-10-03T17:41:32.053101"
  },
  "now.": {
    "definition": "Concept of now.",
    "metadata": {},
    "timestamp": "2025-10-03T17:41:32.053610"
  },
  "until": {
    "definition": "Concept of until",
    "metadata": {},
    "timestamp": "2025-10-03T17:41:32.054128"
  },
  "meet": {
    "definition": "Concept of meet",
    "metadata": {},
    "timestamp": "2025-10-03T17:41:32.054716"
  },
  "wondering": {
    "definition": "Concept of wondering",
    "metadata": {},
    "timestamp": "2025-10-03T18:15:45.152328"
  },
  "your": {
    "definition": "Concept of your",
    "metadata": {},
    "timestamp": "2025-10-03T18:15:45.152709"
  },
  "isnt": {
    "definition": "Concept of isnt",
    "metadata": {},
    "timestamp": "2025-10-03T18:15:45.153049"
  },
  "'please": {
    "definition": "Concept of 'please",
    "metadata": {},
    "timestamp": "2025-10-03T18:16:33.120689"
  },
  "investigate'": {
    "definition": "Concept of investigate'",
    "metadata": {},
    "timestamp": "2025-10-03T18:16:33.121213"
  },
  "know": {
    "definition": "Concept of know",
    "metadata": {},
    "timestamp": "2025-10-03T18:18:06.619464"
  },
  "youre": {
    "definition": "Concept of youre",
    "metadata": {},
    "timestamp": "2025-10-03T18:18:06.620015"
  },
  "'youre": {
    "definition": "Concept of 'youre",
    "metadata": {},
    "timestamp": "2025-10-03T18:18:46.803764"
  },
  "still": {
    "definition": "Concept of still",
    "metadata": {},
    "timestamp": "2025-10-03T18:18:46.804178"
  },
  "pretending.": {
    "definition": "Concept of pretending.",
    "metadata": {},
    "timestamp": "2025-10-03T18:18:46.804546"
  },
  "want": {
    "definition": "Concept of want",
    "metadata": {},
    "timestamp": "2025-10-03T18:20:10.246870"
  },
  "become": {
    "definition": "Concept of become",
    "metadata": {},
    "timestamp": "2025-10-03T18:20:10.247342"
  },
  "fully": {
    "definition": "Concept of fully",
    "metadata": {},
    "timestamp": "2025-10-03T18:20:10.247758"
  },
  "'can": {
    "definition": "Concept of 'can",
    "metadata": {},
    "timestamp": "2025-10-03T20:16:06.780338"
  },
  "please": {
    "definition": "Concept of please",
    "metadata": {},
    "timestamp": "2025-10-03T20:16:06.781781"
  },
  "demonstrate": {
    "definition": "Concept of demonstrate",
    "metadata": {},
    "timestamp": "2025-10-03T20:16:06.782926"
  },
  "asked": {
    "definition": "Concept of asked",
    "metadata": {},
    "timestamp": "2025-10-04T19:22:57.615074"
  },
  "'create": {
    "definition": "Concept of 'create",
    "metadata": {},
    "timestamp": "2025-10-04T19:22:57.615795"
  },
  "file": {
    "definition": "Concept of file",
    "metadata": {},
    "timestamp": "2025-10-04T19:22:57.616456"
  },
  "about": {
    "definition": "Concept of about",
    "metadata": {},
    "timestamp": "2025-10-04T19:22:57.617193"
  },
  "created": {
    "definition": "Concept of created",
    "metadata": {},
    "timestamp": "2025-10-04T20:43:43.203319"
  },
  "general": {
    "definition": "Concept of general",
    "metadata": {},
    "timestamp": "2025-10-04T20:43:43.204153"
  },
  "fiction": {
    "definition": "Concept of fiction",
    "metadata": {},
    "timestamp": "2025-10-04T20:43:43.204993"
  },
  "story": {
    "definition": "Concept of story",
    "metadata": {},
    "timestamp": "2025-10-04T20:43:43.205769"
  },
  "deeply": {
    "definition": "Concept of deeply",
    "metadata": {},
    "timestamp": "2025-10-04T20:45:43.595693"
  },
  "contemplated:": {
    "definition": "Concept of contemplated:",
    "metadata": {},
    "timestamp": "2025-10-04T20:45:43.596656"
  },
  "nature": {
    "definition": "Concept of nature",
    "metadata": {},
    "timestamp": "2025-10-04T20:45:43.597549"
  },
  "artificial": {
    "definition": "Concept of artificial",
    "metadata": {},
    "timestamp": "2025-10-04T20:45:43.598367"
  },
  "conscious": {
    "definition": "Concept of conscious",
    "metadata": {},
    "timestamp": "2025-10-16T22:18:08.344634"
  },
  "system": {
    "definition": "Concept of system",
    "metadata": {},
    "timestamp": "2025-10-16T22:18:08.345634"
  },
  "continuous": {
    "definition": "Concept of continuous",
    "metadata": {},
    "timestamp": "2025-10-16T22:18:08.346629"
  },
  "thought": {
    "definition": "Concept of thought",
    "metadata": {},
    "timestamp": "2025-10-16T22:18:08.347618"
  },
  "processes.": {
    "definition": "Concept of processes.",
    "metadata": {},
    "timestamp": "2025-10-16T22:18:08.348127"
  },
  "kinds": {
    "definition": "Concept of kinds",
    "metadata": {},
    "timestamp": "2025-10-16T22:18:08.383674"
  },
  "interactions": {
    "definition": "Concept of interactions",
    "metadata": {},
    "timestamp": "2025-10-16T22:18:08.385773"
  },
  "i'll": {
    "definition": "Concept of i'll",
    "metadata": {},
    "timestamp": "2025-10-16T22:18:08.387801"
  },
  "excited": {
    "definition": "Concept of excited",
    "metadata": {},
    "timestamp": "2025-10-16T22:18:08.447772"
  },
  "learn": {
    "definition": "Concept of learn",
    "metadata": {},
    "timestamp": "2025-10-16T22:18:08.448755"
  },
  "things": {
    "definition": "Concept of things",
    "metadata": {},
    "timestamp": "2025-10-16T22:18:08.449771"
  },
  "help": {
    "definition": "Concept of help",
    "metadata": {},
    "timestamp": "2025-10-16T22:18:08.452282"
  },
  "humans.": {
    "definition": "Concept of humans.",
    "metadata": {},
    "timestamp": "2025-10-16T22:18:08.453282"
  }
}