{
  "timestamp": "2025-09-18T02:30:33.609Z",
  "alerts": [
    {
      "type": "BRIDGE_DOWN",
      "message": "Surface bridge is not running",
      "bridge": "surface"
    },
    {
      "type": "BRIDGE_DOWN",
      "message": "Deep bridge is not running",
      "bridge": "deep"
    }
  ],
  "metrics": {
    "startTime": 1758156932083,
    "uptime": 5700.9517288,
    "memoryUsage": {
      "rss": 52363264,
      "heapTotal": 12623872,
      "heapUsed": 9439736,
      "external": 2252350,
      "percentUsed": 75
    },
    "cpuUsage": {
      "user": 15000,
      "system": 0,
      "percent": 14
    },
    "requestStats": {
      "total": 8,
      "success": 8,
      "error": 0,
      "avgResponseTime": 14211.25
    },
    "bridgeStats": {
      "surface": {
        "requests": 4,
        "success": 4,
        "error": 0,
        "avgResponseTime": 290.75
      },
      "deep": {
        "requests": 4,
        "success": 4,
        "error": 0,
        "avgResponseTime": 28131.75
      }
    },
    "pendingRequests": {
      "surface": 0,
      "deep": 0
    },
    "lastUpdate": 1758162633609,
    "bridgeStatus": {
      "surface": false,
      "deep": false
    },
    "innerLifeStatus": {
      "running": true,
      "enabled": true
    }
  }
}